py_volanalytics/__init__.py
py_volanalytics/market/__init__.py
py_volanalytics/market/discounting_curve.py
py_volanalytics/market/european_vanilla_option_quote.py
py_volanalytics/math/__init__.py
py_volanalytics/math/interpolator.py
py_volanalytics/models/__init__.py
py_volanalytics/models/vanna_volga/__init__.py
py_volanalytics/models/vanna_volga/vanna_volga.py
py_volanalytics/types/__init__.py
py_volanalytics/types/enums.py
py_volanalytics/types/var_types.py
py_volanalytics/utils/__init__.py
py_volanalytics-0.1.1.dist-info/licenses/LICENSE.txt
py_volanalytics-0.1.1.dist-info/METADATA
py_volanalytics-0.1.1.dist-info/WHEEL
py_volanalytics-0.1.1.dist-info/top_level.txt
py_volanalytics-0.1.1.dist-info/RECORD
