Metadata-Version: 2.4
Name: py_volanalytics
Version: 0.1.1
Summary: Vol-fitting methods and pricing-analytics for volatility derivatives
Home-page: https://github.com/quasar-chunawala/py_volanalytics
Author: quasar-chunawala
Author-email: quasar-chunawala <quasar.chunawala@gmail.com>
Project-URL: Homepage, https://github.com/quasar-chunawala/py_volanalytics
Requires-Python: >=3.12
License-File: LICENSE.txt
Requires-Dist: aleatory>=1.0.1
Requires-Dist: attrs>=25.3.0
Requires-Dist: ipykernel>=6.29.5
Requires-Dist: latex>=0.7.0
Requires-Dist: numpy>=2.2.4
Requires-Dist: scienceplots>=2.1.1
Requires-Dist: matplotlib>=3.10.1
Requires-Dist: setuptools>=77.0.3
Requires-Dist: pip>=25.0.0
Requires-Dist: twine>=6.1.0
Requires-Dist: wheel>=0.45.1
Dynamic: author
Dynamic: home-page
Dynamic: license-file
Dynamic: requires-python
